anchorscad_lib/linear/__init__.py
anchorscad_lib/linear/linear.py
anchorscad_linear-0.1.1.dist-info/METADATA
anchorscad_linear-0.1.1.dist-info/WHEEL
anchorscad_linear-0.1.1.dist-info/licenses/LICENSE
anchorscad_linear-0.1.1.dist-info/RECORD
