Metadata-Version: 2.4
Name: anchorscad-linear
Version: 0.1.1
Summary: Linear algebra API for AnchorSCAD. Includes GMatrix, GVector, translate, rotate, angle and more.
Project-URL: Homepage, https://github.com/owebeeone/anchorscad-linear
Project-URL: Bug Tracker, https://github.com/owebeeone/anchorscad-linear/issues
Author-email: Gianni Mariani <gianni@mariani.ws>
License-File: LICENSE
Classifier: License :: OSI Approved :: GNU Lesser General Public License v2 or later (LGPLv2+)
Classifier: Operating System :: OS Independent
Classifier: Programming Language :: Python :: 3
Requires-Python: >=3.10
Requires-Dist: anchorscad-test-tools
Requires-Dist: numpy
